nostr_publish/__init__.py
nostr_publish/cli.py
nostr_publish/errors.py
nostr_publish/event.py
nostr_publish/frontmatter.py
nostr_publish/models.py
nostr_publish/nak.py
nostr_publish/relay.py
nostr_publish/utils.py
nostr_publish/validator.py
nostr_publish-0.1.0.dist-info/licenses/LICENSE
nostr_publish-0.1.0.dist-info/METADATA
nostr_publish-0.1.0.dist-info/WHEEL
nostr_publish-0.1.0.dist-info/entry_points.txt
nostr_publish-0.1.0.dist-info/top_level.txt
nostr_publish-0.1.0.dist-info/RECORD
