Metadata-Version: 2.4
Name: nostr-publish
Version: 0.1.0
Summary: Markdown to Nostr long-form publisher with NIP-46 remote signing
Author-email: Markus Rother <mail@markusrother.de>
License-Expression: GPL-3.0-or-later
Project-URL: Homepage, https://github.com/941design/emacs-nostr-publish
Project-URL: Repository, https://github.com/941design/emacs-nostr-publish
Project-URL: Issues, https://github.com/941design/emacs-nostr-publish/issues
Classifier: Intended Audience :: Developers
Classifier: Programming Language :: Python :: 3
Classifier: Programming Language :: Python :: 3.9
Classifier: Programming Language :: Python :: 3.10
Classifier: Programming Language :: Python :: 3.11
Classifier: Programming Language :: Python :: 3.12
Classifier: Programming Language :: Python :: 3.13
Classifier: Topic :: Text Editors :: Emacs
Requires-Python: >=3.9
License-File: LICENSE
Requires-Dist: PyYAML>=6.0
Provides-Extra: dev
Requires-Dist: pytest>=7.0; extra == "dev"
Requires-Dist: pytest-timeout>=2.1; extra == "dev"
Requires-Dist: hypothesis>=6.0; extra == "dev"
Requires-Dist: ruff>=0.4.0; extra == "dev"
Dynamic: license-file
